_distance.cpython-310-darwin.so
_features.cpython-310-darwin.so
apollon/__init__.py
apollon/_defaults.py
apollon/aplot.py
apollon/audio.py
apollon/container.py
apollon/datasets.py
apollon/fractal.py
apollon/onsets.py
apollon/segment.py
apollon/tools.py
apollon/types.py
apollon/hmm/__init__.py
apollon/hmm/poisson.py
apollon/hmm/utilities.py
apollon/io/__init__.py
apollon/io/io.py
apollon/io/json.py
apollon/signal/__init__.py
apollon/signal/_features_module.c
apollon/signal/cdim.c
apollon/signal/container.py
apollon/signal/correlogram.c
apollon/signal/critical_bands.py
apollon/signal/features.py
apollon/signal/filter.py
apollon/signal/spectral.py
apollon/signal/tools.py
apollon/som/__init__.py
apollon/som/_distance_module.c
apollon/som/datasets.py
apollon/som/defaults.py
apollon/som/distance.c
apollon/som/neighbors.py
apollon/som/plot.py
apollon/som/som.py
apollon/som/topologies.py
apollon/som/utilities.py
apollon-0.1.6.dist-info/LICENSE.txt
apollon-0.1.6.dist-info/METADATA
apollon-0.1.6.dist-info/WHEEL
apollon-0.1.6.dist-info/top_level.txt
apollon-0.1.6.dist-info/RECORD
