Metadata-Version: 2.1
Name: apollon
Version: 0.1.6
Summary: Feature extraction frame work for content-based music analysis
Author-email: Michael Blaß <mblass@posteo.net>
License: BSD 3-Clause License
Project-URL: Repository, http://github.com/ifsm/apollon
Project-URL: Documentation, https://apollon.readthedocs.io
Keywords: music,analysis,feature extraction
Classifier: License :: OSI Approved :: BSD License
Classifier: Programming Language :: Python :: 3
Classifier: Programming Language :: Python :: 3.9
Classifier: Programming Language :: Python :: 3.10
Classifier: Programming Language :: Python :: 3.11
Classifier: Programming Language :: Python :: 3.12
Classifier: Programming Language :: Python :: 3.13
Classifier: Programming Language :: Python :: 3 :: Only
Classifier: Programming Language :: Python :: Implementation :: CPython
Classifier: Topic :: Scientific/Engineering
Classifier: Topic :: Multimedia :: Sound/Audio :: Analysis
Classifier: Intended Audience :: Science/Research
Classifier: Intended Audience :: Information Technology
Classifier: License :: OSI Approved :: BSD License
Requires-Python: >=3.9
License-File: LICENSE.txt
Requires-Dist: numpy >=1.20
Requires-Dist: jsonschema >=3.2.0
Requires-Dist: scipy >=0.19.0
Requires-Dist: matplotlib >=2
Requires-Dist: pandas >=0.20
Requires-Dist: soundfile >=0.10.2
Requires-Dist: chainsaddiction >=0.2.1
